eisenradio_apk/LICENSE
eisenradio_apk/__init__.py
eisenradio_apk/eisenradio-2.0-arm64-v8a-debug.apk
eisenradio_apk/src/EisenRadio_launcher_round.png
eisenradio_apk/src/eisenradio_android.db
eisenradio_apk/src/in_it.py
eisenradio_apk/src/main.py
eisenradio_apk/src/splash1440.png
eisenradio_apk-2.0.dist-info/LICENSE
eisenradio_apk-2.0.dist-info/METADATA
eisenradio_apk-2.0.dist-info/WHEEL
eisenradio_apk-2.0.dist-info/top_level.txt
eisenradio_apk-2.0.dist-info/RECORD
