Metadata-Version: 2.1
Name: eisenradio-apk
Version: 2.0
Summary: Eisenradio apk installer for Android mobiles
Home-page: 
Author: René Horn
Author-email: rene_horn@gmx.net
License: MIT
Classifier: Programming Language :: Python :: 3
Classifier: License :: OSI Approved :: MIT License
Classifier: Operating System :: OS Independent
Classifier: Development Status :: 5 - Production/Stable
Classifier: Topic :: Multimedia :: Sound/Audio :: Capture/Recording
Requires-Python: >=3.6
License-File: LICENSE
